agepy/__init__.py
agepy/__version__.py
agepy/ageplot/__init__.py
agepy/ageplot/_reference.mplstyle
agepy/ageplot/age.mplstyle
agepy/ageplot/dataviewer.mplstyle
agepy/ageplot/latexbeamer.mplstyle
agepy/ageplot/nature.mplstyle
agepy/ageplot/pccp.mplstyle
agepy/ageplot/powerpoint.mplstyle
agepy/ageplot/prl.mplstyle
agepy/ageplot/tex.mplstyle
agepy/interactive/__init__.py
agepy/interactive/_interactive.py
agepy/interactive/coincedence.py
agepy/interactive/photons.py
agepy/interactive/icons/__init__.py
agepy/interactive/icons/bw-step.svg
agepy/interactive/icons/fw-step.svg
agepy/interactive/icons/roi.svg
agepy/mag/__init__.py
agepy/mag/hysteresis.py
agepy/mag/trajectory.py
agepy/spec/__init__.py
agepy/spec/_anodes.py
agepy/spec/coincidence.py
agepy/spec/photons.py
exp4_agepy-0.2.4.dist-info/METADATA
exp4_agepy-0.2.4.dist-info/WHEEL
exp4_agepy-0.2.4.dist-info/top_level.txt
exp4_agepy-0.2.4.dist-info/RECORD
