Metadata-Version: 2.1
Name: exp4-agepy
Version: 0.2.4
Summary: Python package of Arbeitsgruppe Ehresmann
Author: Adrian Peter Krone
Author-email: adrian.krone@physik.uni-kassel.de
License: "MIT"
Project-URL: docs, https://exp4-agepy.readthedocs.io/en/latest/,
Project-URL: GitHub, https://github.com/exp4-age/agepy
Classifier: Programming Language :: Python :: 3
Classifier: Development Status :: 3 - Alpha
Classifier: Intended Audience :: Education
Classifier: Intended Audience :: Science/Research
Requires-Python: >=3.9
Requires-Dist: matplotlib >=3.7
Requires-Dist: numpy >=1.21
Requires-Dist: scipy >=1.11
Requires-Dist: h5py
Requires-Dist: pandas
